MANIFEST.in
README.rst
camcomskin.padova-configure.zcml
setup.cfg
setup.py
camcomskin/__init__.py
camcomskin.padova.egg-info/PKG-INFO
camcomskin.padova.egg-info/SOURCES.txt
camcomskin.padova.egg-info/dependency_links.txt
camcomskin.padova.egg-info/entry_points.txt
camcomskin.padova.egg-info/namespace_packages.txt
camcomskin.padova.egg-info/not-zip-safe
camcomskin.padova.egg-info/requires.txt
camcomskin.padova.egg-info/top_level.txt
camcomskin/padova/__init__.py
camcomskin/padova/configure.zcml
camcomskin/padova/interfaces.py
camcomskin/padova/portlet_retriever.py
camcomskin/padova/profiles.zcml
camcomskin/padova/setuphandlers.py
camcomskin/padova/skins.zcml
camcomskin/padova/tests.py
camcomskin/padova/upgrades.py
camcomskin/padova/upgrades.zcml
camcomskin/padova/version.txt
camcomskin/padova/browser/__init__.py
camcomskin/padova/browser/configure.zcml
camcomskin/padova/browser/contenttree_widget.py
camcomskin/padova/browser/interfaces.py
camcomskin/padova/browser/login_helper.py
camcomskin/padova/browser/manage_rating.py
camcomskin/padova/browser/pp_homepage_view.py
camcomskin/padova/browser/prenotazioni_view.py
camcomskin/padova/browser/rating_topic_view.py
camcomskin/padova/browser/rating_viewlet.py
camcomskin/padova/browser/register.py
camcomskin/padova/browser/themebaseview.py
camcomskin/padova/browser/tile_collection_renderers.py
camcomskin/padova/browser/tiles_manager_view.py
camcomskin/padova/browser/uffici_list_view.py
camcomskin/padova/browser/viewlet.pt
camcomskin/padova/browser/viewlets.py
camcomskin/padova/browser/images/README.txt
camcomskin/padova/browser/images/arrow_left.svg
camcomskin/padova/browser/images/arrow_right.png
camcomskin/padova/browser/images/arrow_right.svg
camcomskin/padova/browser/images/file.png
camcomskin/padova/browser/images/logo_mini.png
camcomskin/padova/browser/images/menu.png
camcomskin/padova/browser/images/pdf.png
camcomskin/padova/browser/images/print.png
camcomskin/padova/browser/images/rectangle-tool.svg
camcomskin/padova/browser/images/DELETE_ME/bg-notizie.jpg
camcomskin/padova/browser/images/DELETE_ME/bg_menu.jpg
camcomskin/padova/browser/images/DELETE_ME/bg_menu_1.jpg
camcomskin/padova/browser/images/DELETE_ME/bg_menu_2.jpg
camcomskin/padova/browser/images/DELETE_ME/bg_menu_3.jpg
camcomskin/padova/browser/images/DELETE_ME/bg_menu_4.jpg
