Metadata-Version: 1.1
Name: camcomskin.padova
Version: 3.0.1
Summary: CCIAAPD Plone Theme Agid
Home-page: https://github.com/PloneGov-IT/camcomskin.padova
Author: RedTurtle Technology
Author-email: sviluppoplone@redturtle.it
License: GPL
Keywords: web zope plone theme
Platform: UNKNOWN
Classifier: Framework :: Plone
Classifier: Framework :: Plone :: 4.3
Classifier: Programming Language :: Python
